{
  "$schema": "../../schemas/v2/heroes.schema.json",
  "name": "Iron Sorcerer",
  "class": "Conqueror",
  "category": "Spellcaster",
  "movement_type": "Ground",
  "health": 450,
  "population": 0,
  "image_required": true,
  "difficulty": 1,
  "tags": [],
  "abilities": {
    "passive": [
      {
        "name": "Scourge of War",
        "description": "Increases Rank III population, reduces Rank II population."
      },
      {
        "name": "Forges of Valm",
        "description": "Creatures spawned from Buildings have significantly more health."
      },
      {
        "name": "Field Commander",
        "description": "While on the ground, nearby creatures gain a strong defensive buff."
      }
    ],
    "primary": {
      "name": "Twin Strike",
      "description": "Strike with powerful mid-range attacks that interrupt enemies.",
      "damage": 35,
      "mechanics": {
        "cleave": true
      }
    },
    "defense": {
      "name": "Rune Shield",
      "description": "Raise a shield that protects allies and reflects attacks.",
      "charges": 4,
      "duration": 0.5
    },
    "ultimate": {
      "name": "Iron Tempest",
      "description": "Unleash a metal vortex that deals heavy damage, staggers/knocks back all creatures inside.",
      "duration": 3
    }
  },
  "changelog": [
    {
      "version": "0.0.1",
      "date": "2026-02-05T18:35:34.217480Z",
      "description": "Initial Closed Beta 2 Data"
    }
  ],
  "entity_id": "iron_sorcerer",
  "description": "A Conqueror who dominates the battlefield with heavy melee strikes, protective runes, and a metal vortex."
}
